{
    "background": "#130f1e",
    "black": "#342950",
    "blue": "#2b7bbd",
    "brightBlack": "#564585",
    "brightBlue": "#44a3f5",
    "brightCyan": "#54e7f8",
    "brightGreen": "#96e474",
    "brightPurple": "#f76ef1",
    "brightRed": "#ff577e",
    "brightWhite": "#e5dcef",
    "brightYellow": "#f5cb40",
    "cursorColor": "#9675bd",
    "cyan": "#41bac8",
    "foreground": "#cbbade",
    "green": "#76b65b",
    "name": "Ayame",
    "purple": "#9768f8",
    "red": "#c53b5d",
    "selectionBackground": "#4a3168",
    "white": "#8a7d9b",
    "yellow": "#ff874b"
}
